HG22017UNO/__init__.py
HG22017UNO/linear/__init__.py
HG22017UNO/linear/cramer_rule.py
HG22017UNO/linear/gauss_elimination.py
HG22017UNO/linear/gauss_jordan.py
HG22017UNO/linear/lu_decomposition.py
HG22017UNO/nonlinear/__init__.py
HG22017UNO/nonlinear/bisection.py
HG22017UNO/nonlinear/gauss_seidel.py
HG22017UNO/nonlinear/jacobi.py
hg22017uno-0.2.3.dist-info/licenses/LICENSE
solver/__init__.py
solver/nonlinear/__init__.py
solver/nonlinear/bisection.py
solver/nonlinear/gauss_seidel.py
solver/nonlinear/jacobi.py
tests/__init__.py
tests/test_linear_methods.py
tests/test_nonlinear_methods.py
hg22017uno-0.2.3.dist-info/METADATA
hg22017uno-0.2.3.dist-info/WHEEL
hg22017uno-0.2.3.dist-info/top_level.txt
hg22017uno-0.2.3.dist-info/RECORD
